featuremonkey3/__init__.py
featuremonkey3/composer.py
featuremonkey3/helpers.py
featuremonkey3/importhooks.py
featuremonkey3/test/__init__.py
featuremonkey3/test/mock/__init__.py
featuremonkey3/test/mock/composer_mocks.py
featuremonkey3/test/mock/testmodule1.py
featuremonkey3/test/mock/testmodule2.py
featuremonkey3/test/mock/testmodule3.py
featuremonkey3/test/mock/testpackage1/__init__.py
featuremonkey3/test/mock/testpackage1/submodule.py
featuremonkey3/test/test_composer.py
featuremonkey3/tracing/__init__.py
featuremonkey3/tracing/helper.py
featuremonkey3/tracing/logger.py
featuremonkey3/tracing/serializer.py
featuremonkey3-0.1.2.dist-info/LICENSE
featuremonkey3-0.1.2.dist-info/METADATA
featuremonkey3-0.1.2.dist-info/WHEEL
featuremonkey3-0.1.2.dist-info/RECORD
